vhdl/aluControl.vhdl
library ieee;
use ieee.std_logic_1164.all;
entity aluControl is
port(
  i_func : in std_logic_vector(5 downto 0);
  i_aluOP : in std_logic_vector(1 downto 0);
  
  o_operation : out std_logic_vector(2 downto 0)
);
end aluControl;

architecture rtl of aluControl is
  alias f0 : std_logic is i_func(0);
  alias f1 : std_logic is i_func(1);
  alias f2 : std_logic is i_func(2);
  alias f3 : std_logic is i_func(3);
  alias f4 : std_logic is i_func(4);
  alias f5 : std_logic is i_func(5);

  alias op0 : std_logic is i_aluOP(0);
  alias op1 : std_logic is i_aluOP(1);

begin
  o_operation(2) <= (f1 and op1) or op0;
  o_operation(1) <= (not op1) or (not f2);
  o_operation(0) <= (f3 or f0) and op1;

end rtl;

library ieee;
use ieee.std_logic_1164.all;
entity aluControlTB is 
  end aluControlTB;

architecture testbench of aluControlTB is 
  signal clock_tb : std_logic := '0';
  signal sim_end : BOOLEAN := false;

  signal func_TB : std_logic_vector(5 downto 0);
  signal aluOP_TB : std_logic_vector(1 downto 0); 
  signal op_TB : std_logic_vector(2 downto 0);

  constant CLOCK_PERIOD : time := 20 ns;

  component aluControl is
  port(
    i_aluOP : in std_logic_vector(1 downto 0);
    i_func : in std_logic_vector(5 downto 0);
    
    o_operation : out std_logic_vector(2 downto 0)
  );
  end component;

begin
  dut: aluControl
  port map (
    i_func =>  func_TB,
    i_aluOP =>  aluOP_TB,
    o_operation => op_TB
  );

  clock_process:
  process begin
    while (not sim_end) loop
      clock_tb <= '1';
      wait for clock_period / 2;
      clock_tb <= '0';
      wait for clock_period / 2;
    end loop;
    wait;
  end process clock_process;

  stimulus: 
process begin 
  wait for clock_period;

  aluOP_TB <= "00"; func_TB <= "000000";
  wait for clock_period;
  assert op_TB = "010" report "test 1 should be 010";

  aluOP_TB <= "01"; func_TB <= "000000";
  wait for clock_period;
  assert op_TB = "110" report "test 2 should be 110";

  aluOP_TB <= "10"; func_TB <= "000000";
  wait for clock_period;
  assert op_TB = "010" report "test 3 should be 010";

  aluOP_TB <= "10"; func_TB <= "000010";
  wait for clock_period;
  assert op_TB = "110" report "test 4 should be 110";

  aluOP_TB <= "10"; func_TB <= "000100";
  wait for clock_period;
  assert op_TB = "000" report "test 5 should be 000";

  aluOP_TB <= "10"; func_TB <= "000101";
  wait for clock_period;
  assert op_TB = "001" report "test 6 should be 001";

  aluOP_TB <= "10"; func_TB <= "001010";
  wait for clock_period;
  assert op_TB = "111" report "test 7 should be 001";

  sim_end <= true;

end process stimulus;
end testbench;

wave.vcd
$date
  Mon Mar 30 15:32:29 2026
$end
$version
  GHDL v0
$end
$timescale
  1 fs
$end
$scope module standard $end
$upscope $end
$scope module std_logic_1164 $end
$upscope $end
$scope module alucontroltb $end
$var reg 1 ! clock_tb $end
$var reg 1 " sim_end $end
$var reg 6 # func_tb[5:0] $end
$var reg 2 $ aluop_tb[1:0] $end
$var reg 3 % op_tb[2:0] $end
$scope module dut $end
$var reg 6 & i_func[5:0] $end
$var reg 2 ' i_aluop[1:0] $end
$var reg 3 ( o_operation[2:0] $end
$upscope $end
$upscope $end
$enddefinitions $end
#0
1!
0"
bUUUUUU #
bUU $
bUUU %
bUUUUUU &
bUU '
bUUU (
#10000000
0!
#20000000
1!
b000000 #
b00 $
b010 %
b000000 &
b00 '
b010 (
#30000000
0!
#40000000
1!
b01 $
b110 %
b01 '
b110 (
#50000000
0!
#60000000
1!
b10 $
b010 %
b10 '
b010 (
#70000000
0!
#80000000
1!
b000010 #
b110 %
b000010 &
b110 (
#90000000
0!
#100000000
1!
b000100 #
b000 %
b000100 &
b000 (
#110000000
0!
#120000000
1!
b000101 #
b001 %
b000101 &
b001 (
#130000000
0!
#140000000
1!
b001010 #
b111 %
b001010 &
b111 (
#150000000
0!
#160000000
1!
1"
#170000000
0!
#180000000
b000000 #
b00 $
b010 %
b000000 &
b00 '
b010 (
#200000000
b01 $
b110 %
b01 '
b110 (
#220000000
b10 $
b010 %
b10 '
b010 (
#240000000
b000010 #
b110 %
b000010 &
b110 (
#260000000
b000100 #
b000 %
b000100 &
b000 (
#280000000
b000101 #
b001 %
b000101 &
b001 (
#300000000
b001010 #
b111 %
b001010 &
b111 (
#320000000
#340000000
b000000 #
b00 $
b010 %
b000000 &
b00 '
b010 (
#360000000
b01 $
b110 %
b01 '
b110 (
#380000000
b10 $
b010 %
b10 '
b010 (
#400000000
b000010 #
b110 %
b000010 &
b110 (
#420000000
b000100 #
b000 %
b000100 &
b000 (
#440000000
b000101 #
b001 %
b000101 &
b001 (
#460000000
b001010 #
b111 %
b001010 &
b111 (
#480000000
#500000000
b000000 #
b00 $
b010 %
b000000 &
b00 '
b010 (
#520000000
b01 $
b110 %
b01 '
b110 (
#540000000
b10 $
b010 %
b10 '
b010 (
#560000000
b000010 #
b110 %
b000010 &
b110 (
#580000000
b000100 #
b000 %
b000100 &
b000 (
#600000000
b000101 #
b001 %
b000101 &
b001 (
#620000000
b001010 #
b111 %
b001010 &
b111 (
#640000000
#660000000
b000000 #
b00 $
b010 %
b000000 &
b00 '
b010 (
#680000000
b01 $
b110 %
b01 '
b110 (
#700000000
b10 $
b010 %
b10 '
b010 (
#720000000
b000010 #
b110 %
b000010 &
b110 (
#740000000
b000100 #
b000 %
b000100 &
b000 (
#760000000
b000101 #
b001 %
b000101 &
b001 (
#780000000
b001010 #
b111 %
b001010 &
b111 (
#800000000
#820000000
b000000 #
b00 $
b010 %
b000000 &
b00 '
b010 (
#840000000
b01 $
b110 %
b01 '
b110 (
#860000000
b10 $
b010 %
b10 '
b010 (
#880000000
b000010 #
b110 %
b000010 &
b110 (
#900000000
b000100 #
b000 %
b000100 &
b000 (
#920000000
b000101 #
b001 %
b000101 &
b001 (
#940000000
b001010 #
b111 %
b001010 &
b111 (
#960000000
#980000000
b000000 #
b00 $
b010 %
b000000 &
b00 '
b010 (
#1000000000
b01 $
b110 %
b01 '
b110 (
